LICENSE.txt
MANIFEST.in
README.md
setup.cfg
setup.py
./LICENSE.txt
./README.md
./setup.py
./SRPTNG/GetObj.py
./SRPTNG/GetTNGSite.py
./SRPTNG/__init__.py
./SRPTNG/PAOLO/AverHourAngle.py
./SRPTNG/PAOLO/AverParallacticAngle.py
./SRPTNG/PAOLO/MuellerOffsetMatrix.py
./SRPTNG/PAOLO/StokesOffsetVector.py
./SRPTNG/PAOLO/TNGMuellerMatrix.py
./SRPTNG/PAOLO/TNGMuellerMatrixNoDerot.py
./SRPTNG/PAOLO/TNGMuellerMatrixPlate2.py
./SRPTNG/PAOLO/TNGMuellerMatrixPlate4.py
./SRPTNG/PAOLO/TNGMuellerTransmissionMatrix.py
./SRPTNG/PAOLO/__init__.py
./build/lib/SRPTNG/GetObj.py
./build/lib/SRPTNG/GetTNGSite.py
./build/lib/SRPTNG/__init__.py
./build/lib/SRPTNG/PAOLO/AverHourAngle.py
./build/lib/SRPTNG/PAOLO/AverParallacticAngle.py
./build/lib/SRPTNG/PAOLO/MuellerOffsetMatrix.py
./build/lib/SRPTNG/PAOLO/StokesOffsetVector.py
./build/lib/SRPTNG/PAOLO/TNGMuellerMatrix.py
./build/lib/SRPTNG/PAOLO/TNGMuellerMatrixNoDerot.py
./build/lib/SRPTNG/PAOLO/TNGMuellerMatrixPlate2.py
./build/lib/SRPTNG/PAOLO/TNGMuellerMatrixPlate4.py
./build/lib/SRPTNG/PAOLO/TNGMuellerTransmissionMatrix.py
./build/lib/SRPTNG/PAOLO/__init__.py
SRPAstro.TNG.egg-info/PKG-INFO
SRPAstro.TNG.egg-info/SOURCES.txt
SRPAstro.TNG.egg-info/dependency_links.txt
SRPAstro.TNG.egg-info/requires.txt
SRPAstro.TNG.egg-info/top_level.txt
SRPTNG/GetObj.py
SRPTNG/GetTNGSite.py
SRPTNG/__init__.py
SRPTNG/PAOLO/AverHourAngle.py
SRPTNG/PAOLO/AverParallacticAngle.py
SRPTNG/PAOLO/MuellerOffsetMatrix.py
SRPTNG/PAOLO/StokesOffsetVector.py
SRPTNG/PAOLO/TNGMuellerMatrix.py
SRPTNG/PAOLO/TNGMuellerMatrixNoDerot.py
SRPTNG/PAOLO/TNGMuellerMatrixPlate2.py
SRPTNG/PAOLO/TNGMuellerMatrixPlate4.py
SRPTNG/PAOLO/TNGMuellerTransmissionMatrix.py
SRPTNG/PAOLO/__init__.py
Scripts/SRPTNGPAOLOCalStokes
Scripts/SRPTNGPAOLOCut
Scripts/SRPTNGPAOLOInstrStokes
Scripts/SRPTNGPAOLOMergeTables
Scripts/SRPTNGPAOLOParamFit
Scripts/SRPTNGPAOLOSelectCoord
Scripts/SRPTNGPAOLOSelectRow
Scripts/SRPTNGPAOLOSourceMatch
Scripts/SRPTNGPAOLOSpectrumMatch
Scripts/SRPTNGPAOLOStokesSim
Scripts/SRPTNGVersion