Metadata-Version: 2.1
Name: SRPAstro.TNG
Version: 1.2.0
Summary: Tools for the TNG telescope under SRP
Home-page: https://pypi.python.org/pypi/SRPAstro.TNG
Author: Stefano Covino
Author-email: stefano.covino@inaf.it
License: UNKNOWN
Keywords: astronomy data analysis
Platform: UNKNOWN
Classifier: Development Status :: 5 - Production/Stable
Classifier: Environment :: Console
Classifier: Intended Audience :: Science/Research
Classifier: Topic :: Scientific/Engineering :: Astronomy
Classifier: License :: OSI Approved :: MIT License
Classifier: Operating System :: MacOS :: MacOS X
Classifier: Operating System :: Unix
Classifier: Operating System :: POSIX
Classifier: Programming Language :: Python :: 3
Requires-Python: >=3
